MANIFEST.in
README.rst
setup.py
pyjazz/__init__.py
pyjazz/_jazz_blocks2.so
pyjazz/_jazz_blocks3.so
pyjazz/example_google.py
pyjazz/get_jazz_version.py
pyjazz/jazz_blocks.py
pyjazz.egg-info/PKG-INFO
pyjazz.egg-info/SOURCES.txt
pyjazz.egg-info/dependency_links.txt
pyjazz.egg-info/not-zip-safe
pyjazz.egg-info/top_level.txt